my_module/__init__.py
connector_project_01-0.1.0.dist-info/LICENSE
connector_project_01-0.1.0.dist-info/METADATA
connector_project_01-0.1.0.dist-info/WHEEL
connector_project_01-0.1.0.dist-info/top_level.txt
connector_project_01-0.1.0.dist-info/RECORD
