Metadata-Version: 2.1
Name: connector_project_01
Version: 0.1.0
Summary: A brief description of your project
Home-page: https://github.com/Chandani7250/CONNECTOR
Author: Chandani Kumari
Author-email: chandani@chandani.com
License: MIT
Classifier: Programming Language :: Python :: 3
Classifier: License :: OSI Approved :: MIT License
Classifier: Operating System :: OS Independent
Requires-Python: >=3.6
License-File: LICENSE
